{
  "properties": [
    {
      "name": "experimentsFileUploadLocation",
      "type": "java.lang.String",
      "description": "The path for storing experiment files uploaded by the user."
    },
    {
      "name": "kubernetes.deployment.defaults.ram",
      "type": "java.lang.Long",
      "description": "The default value for the RAM if nothing is set."
    },
    {
      "name": "kubernetes.deployment.defaults.cpu",
      "type": "java.lang.Long",
      "description": "The default value for the CPU if nothing is set."
    },
    {
      "name": "kubernetes.deployment.defaults.bookedTime",
      "type": "java.lang.Long",
      "description": "The default value for the booked time if nothing is set."
    },
    {
      "name": "mockdata",
      "type": "java.lang.Boolean",
      "description": "Populates the database with demo data for development purposes."
    },
    {
      "name": "jwt.secret",
      "type": "java.lang.String",
      "description": "The secret used for signing JWTs."
    },
    {
      "name": "mockKubernetesClient",
      "type": "java.lang.String",
      "description": "Set false if you want to use the KubernetesClient."
    },
    {
      "name": "kubernetes.defaultLogLines",
      "type": "java.lang.Integer",
      "description": "Default amount of lines returned when requesting the logs of an active execution without specifying the amount of lines explicitly."
    },
    {
      "name": "dockerRegistry.username",
      "type": "java.lang.String",
      "description": "The users name from which the image should be pulled from the docker registry."
    },
    {
      "name": "dockerRegistry.password",
      "type": "java.lang.String",
      "description": "The password of the user."
    },
    {
      "name": "dockerRegistry.email",
      "type": "java.lang.String",
      "description": "The email-address of the user."
    },
    {
      "name": "dockerRegistry.authKey",
      "type": "java.lang.String",
      "description": "The authentication key of the user."
    },
    {
      "name": "dockerHubRepoPath",
      "type": "java.lang.String",
      "description": "The repository name for the hafenkran docker-hub."
    },
    {
      "name": "kubernetes.debugging",
      "type": "java.lang.Boolean",
      "description": "Set debugging to false in order to use the kubernetes pod informer. If debugging is set to true, kubernetes will throw an exception that it cannot use the pod informer."
    }
  ]
}
